spiralfilm/__init__.py
spiralfilm/config.py
spiralfilm/core.py
spiralfilm/embed.py
spiralfilm/errors.py
spiralfilm/parser.py
spiralfilm/utils.py
SpiralFilm-0.2.5.dist-info/LICENSE
SpiralFilm-0.2.5.dist-info/METADATA
SpiralFilm-0.2.5.dist-info/WHEEL
SpiralFilm-0.2.5.dist-info/top_level.txt
SpiralFilm-0.2.5.dist-info/RECORD
