Metadata-Version: 2.1
Name: SpiralFilm
Version: 0.2.5
Summary: A thin wrapper for the OpenAI GPT family of APIs
Home-page: https://github.com/Spiral-AI/spiralfilm
Author: Yuichi Sasaki
Author-email: y_sasaki@go-spiral.ai
Keywords: openai,gpt,api,wrapper
Classifier: Development Status :: 3 - Alpha
Classifier: Intended Audience :: Developers
Classifier: Topic :: Software Development :: Build Tools
Classifier: License :: OSI Approved :: MIT License
Classifier: Programming Language :: Python :: 3.8
Classifier: Programming Language :: Python :: 3.9
Classifier: Programming Language :: Python :: 3.10
Requires-Python: >=3.8, <4
License-File: LICENSE
Requires-Dist: openai (>=1.0)
Requires-Dist: tiktoken
Requires-Dist: tqdm
Requires-Dist: pytest
